easy_rss/__init__.py
easy_rss/easy_rss.py
easy_rss-1.2.6.dist-info/LICENSE
easy_rss-1.2.6.dist-info/METADATA
easy_rss-1.2.6.dist-info/WHEEL
easy_rss-1.2.6.dist-info/top_level.txt
easy_rss-1.2.6.dist-info/RECORD
