Metadata-Version: 2.1
Name: easy_rss
Version: 1.2.6
Summary: Simple Python package for interacting with RSS feeds
Home-page: https://github.com/michaelMondoro/easy_rss
Author: Michael Mondoro
Author-email: michaelmondoro@gmail.com
Classifier: Programming Language :: Python :: 3
Classifier: License :: OSI Approved :: MIT License
Classifier: Operating System :: OS Independent
Requires-Python: >=3.8
License-File: LICENSE
Requires-Dist: pytz
Requires-Dist: bs4
Requires-Dist: requests
Requires-Dist: python-dateutil
